wlmodem/__init__.py
wlmodem/protocol.py
wlmodem/simulator.py
wlmodem/transport.py
wlmodem/tests/__init__.py
wlmodem/tests/test_protocol.py
wlmodem/tests/test_simulator.py
wlmodem/tests/test_transport.py
wlmodem-1.3.0.dist-info/LICENSE
wlmodem-1.3.0.dist-info/METADATA
wlmodem-1.3.0.dist-info/WHEEL
wlmodem-1.3.0.dist-info/top_level.txt
wlmodem-1.3.0.dist-info/RECORD
