Metadata-Version: 2.1
Name: wlmodem
Version: 1.3.0
Summary: Python library for Water Linked underwater modems
Home-page: https://www.waterlinked.com
Author: Water Linked AS
Author-email: support@waterlinked.com
License: UNKNOWN
Platform: UNKNOWN
Classifier: Development Status :: 4 - Beta
Classifier: Intended Audience :: Developers
Classifier: License :: OSI Approved :: MIT License
Classifier: Programming Language :: Python
Classifier: Programming Language :: Python :: 2
Classifier: Programming Language :: Python :: 2.7
Classifier: Programming Language :: Python :: 3
Classifier: Programming Language :: Python :: 3.6
Classifier: Programming Language :: Python :: 3.7
Classifier: Programming Language :: Python :: Implementation :: CPython
Classifier: Programming Language :: Python :: Implementation :: PyPy
Requires-Dist: setuptools
Requires-Dist: pyserial
Requires-Dist: crcmod
Requires-Dist: cobs
